textgo/__init__.py
textgo/embeddings.py
textgo/metrics.py
textgo/preprocess.py
textgo/textsim.py
textgo/utils.py
textgo/classifier/Bert.py
textgo/classifier/FastText.py
textgo/classifier/TextCNN.py
textgo/classifier/TextRCNN.py
textgo/classifier/TextRNN.py
textgo/classifier/TextRNN_Att.py
textgo/classifier/XLNet.py
textgo/classifier/__init__.py
textgo/classifier/bert.py
textgo/classifier/classifier.py
textgo/classifier/cnn.py
textgo/classifier/download_models.py
textgo/classifier/fasttext.py
textgo/classifier/nn_classifier.py
textgo/classifier/train_eval.py
textgo/classifier/utils.py
textgo/classifier/xgboost.py
textgo/data/stopwords_en.txt
textgo/data/stopwords_zh.txt
textgo-1.4.dist-info/LICENSE
textgo-1.4.dist-info/METADATA
textgo-1.4.dist-info/WHEEL
textgo-1.4.dist-info/entry_points.txt
textgo-1.4.dist-info/top_level.txt
textgo-1.4.dist-info/RECORD
