Metadata-Version: 2.1
Name: textgo
Version: 1.4
Summary: Let's go and play with text!
Home-page: https://github.com/Lipairui/textgo
Author: Pairui Li
Author-email: 953383269@qq.com
License: UNKNOWN
Platform: UNKNOWN
Classifier: License :: OSI Approved :: MIT License
Classifier: Operating System :: OS Independent
Requires-Dist: jieba (>=0.42.1)
Requires-Dist: tqdm (>=4.46.0)
Requires-Dist: transformers (>=2.3.0)
Requires-Dist: numpy (>=1.16.1)
Requires-Dist: torch (>=1.4.0+cu101)
Requires-Dist: pandas (>=0.24.0)
Requires-Dist: gensim (>=3.8.3)
Requires-Dist: scikit-learn (>=0.20.4)
